bert/__init__.py
bert/aws.py
bert/binding.py
bert/constants.py
bert/datasource.py
bert/exceptions.py
bert/naming.py
bert/queues.py
bert/shortcuts.py
bert/utils.py
bert/deploy/__init__.py
bert/deploy/encoders.py
bert/deploy/exceptions.py
bert/deploy/factory.py
bert/deploy/reporting.py
bert/deploy/shortcuts.py
bert/deploy/utils.py
bert/encoders/__init__.py
bert/encoders/base.py
bert/encoders/numpy.py
bert/example/__init__.py
bert/example/exceptions.py
bert/example/factory.py
bert/roles/__init__.py
bert/roles/factory.py
bert/runner/__init__.py
bert/runner/constants.py
bert/runner/factory.py
bert/runner/manager.py
bert/secrets/__init__.py
bert/secrets/factory.py
bert/webservice/__init__.py
bert/webservice/api.py
bert/webservice/handler.py
bert/webservice/manager.py
bert_etl-0.4.68.data/scripts/bert-deploy.py
bert_etl-0.4.68.data/scripts/bert-runner.py
bert_etl-0.4.68.dist-info/LICENSE
bert_etl-0.4.68.dist-info/METADATA
bert_etl-0.4.68.dist-info/WHEEL
bert_etl-0.4.68.dist-info/entry_points.txt
bert_etl-0.4.68.dist-info/top_level.txt
bert_etl-0.4.68.dist-info/RECORD
