Metadata-Version: 2.1
Name: bert-etl
Version: 0.4.68
Summary: A microframework for simple ETL solutions
Home-page: https://github.com/jbcurtin/bert
Author: Joseph Curtin <42@jbcurtin.io
Author-email: bert@jbcurtin.io
License: MIT
Platform: UNKNOWN
Classifier: Operating System :: OS Independent
Classifier: Programming Language :: Python
Classifier: Programming Language :: Python :: 3
Classifier: Programming Language :: Python :: 3.6
Classifier: Programming Language :: Python :: 3.7
Classifier: Programming Language :: Python :: 3 :: Only
Requires-Python: >=3.6
Requires-Dist: redis (==3.3.5)
Requires-Dist: marshmallow (==2.19.5)
Requires-Dist: boto3 (==1.9.251)
Requires-Dist: pyyaml (==5.1.2)
Requires-Dist: GitPython (==3.1.1)
